{
  "id": "고용노동부-2026-06-09-b04458a0",
  "category": "고용",
  "subcategory": "고용",
  "title": "2026년 5월 고용행정 통계로 본 노동시장 동향",
  "source": "고용노동부",
  "source_url": "https://www.korea.kr/briefing/pressReleaseView.do?newsId=156765764&call_from=openData",
  "file_url": "https://www.korea.kr/common/download.do?tblKey=GMN&fileId=198485784",
  "file_type": "hwpx",
  "published_at": "2026-06-09T14:28:31+09:00",
  "crawled_at": "2026-06-11T02:56:16.079646+09:00",
  "summary": {
    "what_changed": "2026년 5월 고용보험 상시가입자는 전년 동월 대비 26만 8천명(+1.7%) 증가했으며, 신규 구인은 1만 2천명(+8.7%) 증가하고 신규 구직은 1만 2천명(-3.3%) 감소하여 구인배수(구직자 1인당 일자리수)가 0.42로 상승했습니다.",
    "who_is_affected": "고용보험 가입자는 서비스업(특히 보건복지), 30대, 50대, 60세 이상에서 증가했으나, 제조업, 건설업 및 29세 이하, 40대에서는 감소했습니다. 신규 구직은 29세 이하에서 증가하고 30대, 40대, 50대, 60세 이상에서는 감소했습니다.",
    "when_effective": "2026년 5월 (통계 기준)",
    "key_points": [
      "고용보험 상시가입자가 1,584만 8천명으로 전년 동월 대비 26만 8천명(+1.7%) 증가.",
      "서비스업(보건복지 등) 가입자는 증가하고, 제조업 및 건설업 가입자는 감소세 지속.",
      "구직급여 신규신청자는 7.2% 감소, 지급자 및 지급액은 6.0% 및 7.0% 감소.",
      "신규구인은 8.7% 증가하고 신규구직은 3.3% 감소하여 구인배수 0.42로 상승."
    ]
  }
}