{
  "id": "방위사업청-2026-06-15-b8dd3561",
  "category": "고용",
  "subcategory": "고용",
  "title": "[방사청·고용노동부·소방청 공동] 군용화약류 취급 사업장 전수 합동점검 실시",
  "source": "방위사업청",
  "source_url": "https://www.korea.kr/briefing/pressReleaseView.do?newsId=156766577&call_from=openData",
  "file_url": "https://www.korea.kr/common/download.do?tblKey=GMN&fileId=198489430",
  "file_type": "pdf",
  "published_at": "2026-06-15T15:32:00+09:00",
  "crawled_at": "2026-06-15T18:57:26.033104+09:00",
  "summary": {
    "what_changed": "고용노동부, 방위사업청, 소방청이 공동으로 전국의 42개 군용화약류 취급 사업장에 대해 한화에어로스페이스 폭발사고를 계기로 전수 합동점검을 실시합니다.",
    "who_is_affected": "전국의 42개 군용화약류 제조·저장·취급 사업장 및 해당 사업장의 작업 노동자들이 직접적인 점검 대상입니다.",
    "when_effective": "6월 15일부터",
    "key_points": [
      "고용노동부, 방위사업청, 소방청, 국방과학연구소 및 한국산업안전보건공단이 참여하는 합동점검반이 구성됩니다.",
      "군용화약류 제조·저장·시험 등 모든 공실의 안전관리 실태와 잔여 화약류 세척 등 위험 요인 공정의 안전조치를 집중 점검하며, 노동자 의견을 청취하여 무허가 취급 여부를 확인합니다.",
      "「산업안전보건법」, 「방위사업법」, 「위험물안전관리법」 준수 여부를 중점 점검하고, 위반 시 관계 법령에 따라 조치하며 현장 안전수준 제고를 위한 개선 권고 및 지도를 병행합니다."
    ]
  }
}