{
  "id": "재정경제부-2026-05-31-731d90ee",
  "category": "고용",
  "subcategory": "고용",
  "title": "세계은행그룹, 'AI·디지털 기술' 분야  한국인 우수 인재 유치를 위한 채용 미션 개최",
  "source": "재정경제부",
  "source_url": "https://www.korea.kr/briefing/pressReleaseView.do?newsId=156764566&call_from=openData",
  "file_url": "https://www.korea.kr/common/download.do?tblKey=GMN&fileId=198478969",
  "file_type": "hwpx",
  "published_at": "2026-05-31T00:00:00+09:00",
  "crawled_at": "2026-06-11T03:01:51.257788+09:00",
  "summary": {
    "what_changed": "세계은행그룹이 한국의 AI 및 디지털 기술 분야 우수 인재를 유치하기 위해 7월 1일부터 7월 3일까지 한국에서 채용 미션을 개최할 예정입니다.",
    "who_is_affected": "한국의 우수한 AI 및 디지털 기술 분야 인재들이 대상이며, 세계은행그룹에 취업을 희망하는 한국인 전문가들이 해당됩니다.",
    "when_effective": "7월 1일(수) ~ 7월 3일(금)",
    "key_points": [
      "세계은행그룹 인사부서, 한국 방한하여 채용 미션 개최",
      "모집 대상 분야: AI 및 디지털 기술",
      "채용 미션 기간은 7월 1일(수)부터 7월 3일(금)까지",
      "자세한 내용은 첨부 파일을 참고하며, 문의는 재정경제부 개발금융총괄과(044-215-8719)로 가능"
    ],
    "background": "세계은행그룹은 한국의 우수하고 뛰어난 인공지능(AI) 및 디지털 기술 분야 인재를 채용하고 확보하기 위해 이번 행사를 마련했습니다.",
    "eligibility": [
      "한국인이어야 합니다.",
      "AI 또는 디지털 기술 분야의 전문가여야 합니다.",
      "세계은행그룹에서 일하기를 희망해야 합니다."
    ],
    "faq": [
      {
        "question": "이번 채용 행사는 누구를 위한 것인가요?",
        "answer": "세계은행그룹에 취업을 희망하는 한국인 인공지능(AI) 및 디지털 기술 분야 전문가를 대상으로 합니다."
      },
      {
        "question": "채용 행사는 언제 열리나요?",
        "answer": "7월 1일 수요일부터 7월 3일 금요일까지 3일간 한국에서 진행됩니다."
      },
      {
        "question": "어떤 분야의 인재를 모집하나요?",
        "answer": "인공지능(AI) 및 디지털 기술 분야의 인재를 모집합니다."
      },
      {
        "question": "채용 행사에 대해 더 자세히 문의할 곳이 있나요?",
        "answer": "재정경제부 개발금융총괄과(044-215-8719)로 문의할 수 있습니다."
      },
      {
        "question": "어떻게 지원할 수 있나요?",
        "answer": "본 문서에는 구체적인 지원 방법이 나와 있지 않으며, '첨부 파일'을 참고해야 한다고 명시되어 있습니다."
      }
    ],
    "glossary": [
      {
        "term": "세계은행그룹",
        "definition": "전 세계적으로 개발도상국의 경제 발전과 빈곤을 줄이는 것을 목표로 하는 국제적인 금융 기관들의 모임입니다."
      },
      {
        "term": "채용 미션",
        "definition": "어떤 기관이 필요한 인재를 뽑기 위해 특정 국가나 지역을 찾아가서 진행하는 채용 활동이나 행사를 말합니다."
      },
      {
        "term": "인사부서",
        "definition": "회사나 조직에서 직원의 채용, 교육, 급여, 복지 등 사람과 관련된 업무를 담당하는 부서입니다."
      },
      {
        "term": "방한",
        "definition": "외국인이 한국을 방문하는 것을 뜻하는 말입니다."
      },
      {
        "term": "재정경제부 개발금융총괄과",
        "definition": "정부 부처의 한 부서로, 국가의 재정(돈)을 관리하고 개발도상국을 돕기 위한 금융(자금) 지원과 국제적인 협력 업무를 총괄(전체적으로 관리)하는 곳입니다."
      }
    ]
  }
}