{
  "subcategory": "복지",
  "items": [
    {
      "id": "보건복지부-2026-07-19-00acb588",
      "title": "더 나은 보건복지 상담 위해 국민의 의견을 들려주세요.",
      "published_at": "2026-07-19T12:05:00+09:00"
    },
    {
      "id": "보건복지부-2026-07-16-89e14b4d",
      "title": "생명 살리고, 돌봄 넓히고, 지역의료 키운다. 「보건복지부 업무계획」 발표",
      "published_at": "2026-07-16T16:48:02+09:00"
    },
    {
      "id": "행정안전부-2026-07-15-c6ecc715",
      "title": "고유가 피해지원금 지급 등 탁월한 성과 낸 주역들에게 특별성과포상금 신속 수여",
      "published_at": "2026-07-15T17:30:00+09:00"
    },
    {
      "id": "국민권익위원회-2026-07-15-0e392bbb",
      "title": "\"취약계층의 권익 보호를 위해\"… 복지·민원 담당자, 함께 모여 업무역량 높인다",
      "published_at": "2026-07-15T12:43:00+09:00"
    },
    {
      "id": "산림청-2026-07-14-fc42cb8a",
      "title": "북부지방산림청, 장마·폭염 대비 산림복지 다중이용시설 안전관리 강화",
      "published_at": "2026-07-14T16:52:19+09:00"
    },
    {
      "id": "보건복지부-2026-07-14-56a08e0a",
      "title": "보건복지부 조직 전면 개편으로 지역·필수·공공의료 강화 등 핵심 동력 확보",
      "published_at": "2026-07-14T13:50:15+09:00"
    },
    {
      "id": "보건복지부-2026-07-14-3109cc3d",
      "title": "여름철 취약계층 폭염·풍수해 걱정 없도록 사회복지시설 안전 점검 강화방안 논의",
      "published_at": "2026-07-14T13:26:05+09:00"
    },
    {
      "id": "산림청-2026-07-13-29531140",
      "title": "산림청, 여름철 집중호우, 폭염 대비  산림복지시설 재난안전 점검",
      "published_at": "2026-07-13T16:17:01+09:00"
    },
    {
      "id": "보건복지부-2026-07-13-78a80496",
      "title": "지역 복지 사각지대 대응 위해 복지부와 KMI가 손잡는다",
      "published_at": "2026-07-13T14:03:03+09:00"
    },
    {
      "id": "보건복지부-2026-07-10-94223308",
      "title": "중앙-지방 협력 강화해 통합돌봄 등 지역 현장 복지 체감 높인다",
      "published_at": "2026-07-10T10:35:00+09:00"
    },
    {
      "id": "국무조정실-2026-07-10-85db2ae4",
      "title": "[보도자료]  천명수호처 한국산림복지진흥원, 중장년 생명지킴 산림치유사업 추진",
      "published_at": "2026-07-10T10:34:08+09:00"
    },
    {
      "id": "보건복지부-2026-07-09-30536aac",
      "title": "2025년 사회복지시설 평가 결과, '절반 이상 A등급' 양질의 서비스 제공받는다",
      "published_at": "2026-07-09T12:05:00+09:00"
    },
    {
      "id": "보건복지부-2026-07-09-ff9b8fa8",
      "title": "\"취약 채무자의 복지위기 빠짐없이 찾아낸다\" 금융 위기가구 발굴 및 지원 강화 방안 발표",
      "published_at": "2026-07-09T11:05:00+09:00"
    },
    {
      "id": "보건복지부-2026-07-08-6f612f33",
      "title": "복지부, '악역이 필요 없는 시대-빌런 3부작' 공개 5일 만에 누적 조회수 300만 회 돌파",
      "published_at": "2026-07-08T14:24:30+09:00"
    },
    {
      "id": "보건복지부-2026-07-08-07312bdc",
      "title": "\"청년이 느끼는 불편함, 청년이 직접 손본다\" 제4기 보건복지부 2030청년자문단 발대식 개최",
      "published_at": "2026-07-08T14:05:00+09:00"
    },
    {
      "id": "보건복지부-2026-07-08-fc889bfe",
      "title": "이사해도 복지서비스는 그대로 사회보장 전산관리번호 7월 9일 개편·시행",
      "published_at": "2026-07-08T12:05:00+09:00"
    },
    {
      "id": "중소벤처기업부-2026-07-07-806d92e6",
      "title": "중기부, 고환율 피해 수출기업을 위한 수출바우처 3차 모집 실시",
      "published_at": "2026-07-07T13:16:54+09:00"
    },
    {
      "id": "보건복지부-2026-07-06-e385511a",
      "title": "민·관·학 협력해 AI 시대 사회문제 해결할 사회복지 AI 혁신 인재 키운다",
      "published_at": "2026-07-06T08:18:41+09:00"
    },
    {
      "id": "행정안전부-2026-07-04-a46422a3",
      "title": "(보도참고자료) 고유가 피해지원금 신청·지급 마감 결과(7.3. 18시 기준)",
      "published_at": "2026-07-04T12:00:00+09:00"
    },
    {
      "id": "농림축산식품부-2026-07-02-65c6a2c8",
      "title": "농식품부, 동물복지 산란계 농장 꼼꼼히 살폈다.",
      "published_at": "2026-07-02T14:04:21+09:00"
    },
    {
      "id": "보건복지부-2026-07-02-3bc6a99b",
      "title": "AI가 국민 삶의 질 높이는데 활용되도록 AI 제대로 쓰는 보건복지부 만든다",
      "published_at": "2026-07-02T11:04:49+09:00"
    },
    {
      "id": "보건복지부-2026-06-30-7eb49f5c",
      "title": "'나의 긍정양육 점수는?' 보건복지부, 부모교육 확산 이벤트 진행",
      "published_at": "2026-06-30T12:05:00+09:00"
    },
    {
      "id": "보건복지부-2026-06-29-30992833",
      "title": "\"음료는 잘 드시고 계신가요?\" 민관협력 통해 문 앞까지 찾아가는 복지 구현",
      "published_at": "2026-06-29T17:30:13+09:00"
    },
    {
      "id": "농림축산식품부-2026-06-29-6ce950a2",
      "title": "2025년 동물보호·복지 실태조사 결과 발표",
      "published_at": "2026-06-29T11:00:00+09:00"
    },
    {
      "id": "보건복지부-2026-06-29-b81c2962",
      "title": "전남광주통합특별시 출범 등에 따른 사회보장정보시스템 대규모 전환 작업 실시",
      "published_at": "2026-06-29T09:56:20+09:00"
    },
    {
      "id": "고용노동부-2026-06-29-ac714999",
      "title": "\"소음성 난청 산재 장해보상 빨라진다\" 근로복지공단, 소음성 난청 산재보상 청력검사 특진 의료기관 확대",
      "published_at": "2026-06-29T09:49:34+09:00"
    },
    {
      "id": "행정안전부-2026-06-29-6b9350c5",
      "title": "「고유가 피해지원금」 7월 3일 18시까지 꼭 신청하세요",
      "published_at": "2026-06-29T09:00:00+09:00"
    },
    {
      "id": "중소벤처기업부-2026-06-29-0f63ea0a",
      "title": "고유가 피해지원금 효과로 골목상권 매출 10.6% 증가(전년 동기 대비, 지급 후 3주간)",
      "published_at": "2026-06-29T06:40:05+09:00"
    },
    {
      "id": "보건복지부-2026-06-26-bd1077ed",
      "title": "복지서비스 질 직결되는 종사자 처우 개선한다, 사회복지시설 인건비 가이드라인 준수율 100% 달성 추진",
      "published_at": "2026-06-26T16:01:26+09:00"
    },
    {
      "id": "보건복지부-2026-06-26-d04399b7",
      "title": "전남·광주 통합에 '복지 패스트트랙' 가동, 행정부담 줄고 주민 혜택 빨라진다",
      "published_at": "2026-06-26T14:05:00+09:00"
    }
  ]
}