{
  "subcategory": "부동산",
  "items": [
    {
      "id": "행정중심복합도시건설-2026-06-11-53b6aebf",
      "title": "몽골 정부 행복도시 방문, 신도시 개발 협력 박차",
      "published_at": "2026-06-11T17:02:00+09:00"
    },
    {
      "id": "국무조정실-2026-06-11-a43f2115",
      "title": "[보도자료] 제15차 부동산 불법행위 대응 협의회",
      "published_at": "2026-06-11T15:43:00+09:00"
    },
    {
      "id": "금융위원회-2026-06-11-9d2ff324",
      "title": "현재 유포되고 있는 부동산 종합 대책 관련 게시글의 보도에 유의하여 주시기 바랍니다.",
      "published_at": "2026-06-11T00:00:00+09:00"
    },
    {
      "id": "국토교통부-2026-06-10-60c8d622",
      "title": "[참고] 현재 유포되고 있는 부동산 종합 대책 관련 게시글의 보도에 유의하여 주시기 바랍니다.",
      "published_at": "2026-06-10T21:02:00+09:00"
    },
    {
      "id": "국토교통부-2026-04-06-753cfa47",
      "title": "개발제한구역 주민의 생업·주거 관련불편사항 개선된다",
      "published_at": "2026-04-06T13:31:00+09:00"
    },
    {
      "id": "금융위원회-2026-04-06-1c120c38",
      "title": "부동산 프로젝트 금융(PF) 상황 점검회의 개최",
      "published_at": "2026-04-06T00:00:00+09:00"
    },
    {
      "id": "국토교통부-2026-04-09-527228cb",
      "title": "김용석 대광위원장,\"양주신도시 교통망 신속구축\"으로 교통불편 최소화",
      "published_at": "2026-04-09T16:41:00+09:00"
    },
    {
      "id": "국토교통부-2026-04-09-64404e94",
      "title": "부동산감독추진단, 제11차 부동산 불법행위 대응협의회 개최",
      "published_at": "2026-04-09T11:00:00+09:00"
    },
    {
      "id": "국세청-2026-04-09-3442de5c",
      "title": "부동산 탈세 신고하면 최대 40억 원 포상금 지급",
      "published_at": "2026-04-09T11:00:00+09:00"
    },
    {
      "id": "국민권익위원회-2026-04-09-936ae582",
      "title": "\"주택 소유권자인 모친이 돌아가셨지만\"… 20년 넘게 함께 거주한 아들, '이축' 허용해야",
      "published_at": "2026-04-09T10:31:54+09:00"
    },
    {
      "id": "재정경제부-2026-04-09-75ab0014",
      "title": "다주택자에 대한 양도소득세 중과 유예 종료 적용 보완 추진",
      "published_at": "2026-04-09T10:00:38+09:00"
    },
    {
      "id": "국토교통부-2026-04-09-ae46c8d2",
      "title": "다주택자에 대한 양도소득세 중과  유예 종료 적용 보완 추진",
      "published_at": "2026-04-09T10:00:00+09:00"
    },
    {
      "id": "국무조정실-2026-04-09-d11bd15b",
      "title": "[보도자료] 제11차 부동산 불법행위 대응 협의회 보도자료",
      "published_at": "2026-04-09T09:51:52+09:00"
    },
    {
      "id": "국토교통부-2026-04-13-3a1a3827",
      "title": "\"새만금에 일자리·주거·교통 함께 들어선다\" 새만금 투자지원 TF 본격 가동",
      "published_at": "2026-04-13T16:00:00+09:00"
    },
    {
      "id": "기후에너지환경부-2026-04-16-68e31b8b",
      "title": "공동주택 내 전기차 충전시설 설치·운영체계 개선을 위한 간담회 개최",
      "published_at": "2026-04-16T10:00:00+09:00"
    },
    {
      "id": "국토교통부-2026-04-15-c4e482b3",
      "title": "올해 수도권 공공주택 6만호 이상 착공",
      "published_at": "2026-04-15T15:00:00+09:00"
    },
    {
      "id": "국토교통부-2026-04-15-76adfa58",
      "title": "대광위, 신도시 교통대책 협력체계 가동 \"속도는 높이고, 주민 불편은 낮춘다\"",
      "published_at": "2026-04-15T11:00:00+09:00"
    },
    {
      "id": "행정중심복합도시건설-2026-04-22-e735ca54",
      "title": "행복도시, 세계가 찾는 신도시 모델로 부상",
      "published_at": "2026-04-22T14:32:00+09:00"
    },
    {
      "id": "소방청-2026-04-21-4b69c9a2",
      "title": "\"불나면 무조건 대피? '상황별 피난 행동요령'에 따르세요\" 소방청, 아파트 화재 피난 수칙 강조",
      "published_at": "2026-04-21T07:00:00+09:00"
    },
    {
      "id": "국토교통부-2026-04-20-2f3a39fa",
      "title": "지역주택조합 '희망고문' 멈춘다… \"조합원 피해 예방 및 사업 정상화 방안 발표\"",
      "published_at": "2026-04-20T16:00:00+09:00"
    },
    {
      "id": "국토교통부-2026-04-23-50ba80f8",
      "title": "서울·경기지역 주택 이상거래 집중 기획조사 결과 발표···위법 의심거래 746건 적발",
      "published_at": "2026-04-23T16:30:00+09:00"
    },
    {
      "id": "국무조정실-2026-04-23-2a9c8fb1",
      "title": "[보도자료] 제12차 부동산 불법행위 대응 협의회",
      "published_at": "2026-04-23T09:54:00+09:00"
    },
    {
      "id": "국토교통부-2026-04-30-dde23bd8",
      "title": "'26년 3월 주택통계",
      "published_at": "2026-04-30T06:00:00+09:00"
    },
    {
      "id": "국토교통부-2026-04-29-c74b7da7",
      "title": "2026년 공동주택 공시가격 결정·공시",
      "published_at": "2026-04-29T11:00:00+09:00"
    },
    {
      "id": "국토교통부-2026-05-07-6f004719",
      "title": "[참고] 「국토계획법」·「토지보상법」·「부동산거래신고법」 개정안 국회 본회의 통과",
      "published_at": "2026-05-07T19:25:00+09:00"
    },
    {
      "id": "국토교통부-2026-05-08-566bf351",
      "title": "2026년 1분기 '부동산서비스산업 기업경기조사' 국가승인통계 첫 공표",
      "published_at": "2026-05-08T06:00:00+09:00"
    },
    {
      "id": "재정경제부-2026-05-08-35e4fe4d",
      "title": "비상경제본부 회의 겸 경제·부동산관계장관회의 개최",
      "published_at": "2026-05-08T00:00:00+09:00"
    },
    {
      "id": "국토교통부-2026-05-12-7e09a727",
      "title": "세입자 있는 주택 전체로 토지거래허가구역 실거주 유예 확대",
      "published_at": "2026-05-12T11:30:00+09:00"
    },
    {
      "id": "기후에너지환경부-2026-05-15-7443eb68",
      "title": "공동주택에도 수열에너지 보급 확대… 민관 주도 발전협의체 출범",
      "published_at": "2026-05-15T10:00:00+09:00"
    },
    {
      "id": "재정경제부-2026-05-15-710b9f8c",
      "title": "부동산관계장관회의 개최",
      "published_at": "2026-05-15T00:00:00+09:00"
    }
  ]
}